itipy/__init__.py
itipy/callback.py
itipy/iti.py
itipy/trainer.py
itipy/translate.py
itipy/data/__init__.py
itipy/data/align.py
itipy/data/baseline_calibration.py
itipy/data/convert.py
itipy/data/data_module.py
itipy/data/dataset.py
itipy/data/editor.py
itipy/data/euv_calibration.py
itipy/data/loader.py
itipy/data/hinode/__init__.py
itipy/data/hinode/classify.py
itipy/data/hinode/clean.py
itipy/data/hinode/plot.py
itipy/data/sdo/__init__.py
itipy/data/sdo/clean.py
itipy/data/sdo/hmi_psf.py
itipy/data/sdo/hmi_statistic.py
itipy/data/sdo/norm_limits.py
itipy/data/sdo/samples.py
itipy/data/soho/__init__.py
itipy/data/soho/analyse.py
itipy/data/soho/clean.py
itipy/data/soho/norm_limits.py
itipy/data/soho/plot.py
itipy/data/soho/samples.py
itipy/data/stereo/__init__.py
itipy/data/stereo/clean.py
itipy/data/stereo/degradation.py
itipy/data/stereo/norm_limits.py
itipy/data/stereo/plot.py
itipy/data/stereo/samples.py
itipy/data/util/__init__.py
itipy/data/util/feature_patch.py
itipy/download/__init__.py
itipy/download/download_hinode.py
itipy/download/download_hmi_continuum.py
itipy/download/download_hmi_video.py
itipy/download/download_kso_synoptic.py
itipy/download/download_proba2.py
itipy/download/download_sdo.py
itipy/download/download_sdo_comparison.py
itipy/download/download_sdo_jsoc.py
itipy/download/download_soho.py
itipy/download/download_solo.py
itipy/download/download_stereo.py
itipy/download/download_stereo_synchronic.py
itipy/evaluation/__init__.py
itipy/evaluation/compute_fid.py
itipy/evaluation/euv_comparison.py
itipy/evaluation/evaluate_kso_quality.py
itipy/evaluation/evaluate_sdo_mag.py
itipy/evaluation/evaluate_soho_sdo_overlap.py
itipy/evaluation/evaluate_soho_sdo_subset.py
itipy/evaluation/fid_stereo.py
itipy/evaluation/metrics.py
itipy/evaluation/plot_datasets.py
itipy/evaluation/plot_kso.py
itipy/evaluation/plot_kso_sample.py
itipy/evaluation/plot_kso_variation.py
itipy/evaluation/plot_soho_sdo_cycle.py
itipy/evaluation/plot_soho_sdo_full.py
itipy-0.1.1.dist-info/LICENSE
itipy-0.1.1.dist-info/METADATA
itipy-0.1.1.dist-info/WHEEL
itipy-0.1.1.dist-info/top_level.txt
itipy-0.1.1.dist-info/RECORD
