Metadata-Version: 2.1
Name: itipy
Version: 0.1.1
Summary: Package for translation between image domains of different astrophysical instruments.
Home-page: https://github.com/RobertJaro/InstrumentToInstrument
Author: Robert Jarolim
License: GNU GENERAL PUBLIC LICENSE
License-File: LICENSE
Requires-Dist: torch >=1.8
Requires-Dist: sunpy >=2.0
Requires-Dist: scikit-image
Requires-Dist: scikit-learn
Requires-Dist: tqdm
Requires-Dist: numpy
Requires-Dist: matplotlib
Requires-Dist: astropy
Requires-Dist: aiapy
Requires-Dist: drms
Requires-Dist: jupyter
Requires-Dist: sunpy-soar
Requires-Dist: lightning
Requires-Dist: google
Requires-Dist: google-cloud-storage
Requires-Dist: wandb
Requires-Dist: pytorch-fid
